CHANGES
MANIFEST.in
README.rst
setup.cfg
setup.py
cuevanalib/__init__.py
cuevanalib/cuevanaapi.py
cuevanalib/downloaders.py
cuevanalib/progressbar_widgets.py
cuevanalib/utils.py
cuevanalib.egg-info/PKG-INFO
cuevanalib.egg-info/SOURCES.txt
cuevanalib.egg-info/dependency_links.txt
cuevanalib.egg-info/requires.txt
cuevanalib.egg-info/top_level.txt
tests/local/_box_1076.jpg
tests/local/_box_910.jpg
tests/local/_box_997.jpg
tests/local/_buscar_-q=a+non+existent+content-cat=titulo
tests/local/_buscar_-q=alexandre+rodrigues-cat=actor
tests/local/_buscar_-q=bielinsky-cat=director
tests/local/_buscar_-q=hamsterdam-cat=episodio
tests/local/_buscar_-q=matrix-cat=titulo
tests/local/_download_sub-file=s_sub_3309_ES.srt
tests/local/_download_sub-file=sub_997_ES.srt
tests/local/_list_search_id.php-serie=115
tests/local/_list_search_id.php-serie=1460
tests/local/_list_search_id.php-serie=1619
tests/local/_list_search_id.php-serie=1912
tests/local/_list_search_id.php-serie=3651
tests/local/_list_search_id.php-serie=3805
tests/local/_list_search_id.php-serie=3875
tests/local/_list_search_id.php-serie=450
tests/local/_list_search_id.php-serie=68
tests/local/_list_search_id.php-serie=910
tests/local/_list_search_id.php-temporada=178
tests/local/_list_search_id.php-temporada=184
tests/local/_list_search_id.php-temporada=192
tests/local/_list_search_id.php-temporada=200
tests/local/_list_search_id.php-temporada=205
tests/local/_list_search_id.php-temporada=211
tests/local/_list_search_id.php-temporada=220
tests/local/_list_search_id.php-temporada=229
tests/local/_list_search_id.php-temporada=29
tests/local/_list_search_id.php-temporada=552
tests/local/_list_search_id.php-temporada=821
tests/local/_list_search_info.php-serie=115
tests/local/_list_search_info.php-serie=1460
tests/local/_list_search_info.php-serie=1619
tests/local/_list_search_info.php-serie=1912
tests/local/_list_search_info.php-serie=3651
tests/local/_list_search_info.php-serie=3805
tests/local/_list_search_info.php-serie=3875
tests/local/_list_search_info.php-serie=450
tests/local/_list_search_info.php-serie=68
tests/local/_list_search_info.php-serie=910
