Metadata-Version: 1.0
Name: cuevanalib
Version: 0.6
Summary: A lib trying to work as cuevana.tv missing API
Home-page: https://bitbucket.org/tin_nqn/cuevanalib
Author: Martín Gaitán
Author-email: gaitan@gmail.com
License: GNU GENERAL PUBLIC LICENCE v3.0 (see LICENCE.txt)
Platform: UNKNOWN
Classifier: Development Status :: 4 - Beta
Classifier: Environment :: Console
Classifier: Intended Audience :: Developers
Classifier: License :: OSI Approved :: GNU General Public License (GPL)
Classifier: Natural Language :: English
Classifier: Operating System :: OS Independent
Classifier: Programming Language :: Python
Classifier: Topic :: Internet :: WWW/HTTP :: Dynamic Content
